foundation/__init__.py
foundation/http.py
foundation/json.py
foundation/predicates.py
foundation/py.typed
foundation/string.py
foundation/string_utils.py
foundation/core/__init__.py
foundation/core/optional/__init__.py
icloudpd/__init__.py
icloudpd/authentication.py
icloudpd/autodelete.py
icloudpd/base.py
icloudpd/cli.py
icloudpd/config.py
icloudpd/constants.py
icloudpd/counter.py
icloudpd/download.py
icloudpd/email_notifications.py
icloudpd/exif_datetime.py
icloudpd/filename_policies.py
icloudpd/log_level.py
icloudpd/logger.py
icloudpd/mfa_provider.py
icloudpd/password_provider.py
icloudpd/paths.py
icloudpd/progress.py
icloudpd/py.typed
icloudpd/status.py
icloudpd/string_helpers.py
icloudpd/xmp_sidecar.py
icloudpd/server/__init__.py
icloudpd-1.32.2.dist-info/licenses/LICENSE.md
pyicloud_ipd/__init__.py
pyicloud_ipd/asset_version.py
pyicloud_ipd/base.py
pyicloud_ipd/cmdline.py
pyicloud_ipd/exceptions.py
pyicloud_ipd/file_match.py
pyicloud_ipd/item_type.py
pyicloud_ipd/live_photo_mov_filename_policy.py
pyicloud_ipd/py.typed
pyicloud_ipd/raw_policy.py
pyicloud_ipd/session.py
pyicloud_ipd/sms.py
pyicloud_ipd/utils.py
pyicloud_ipd/version_size.py
pyicloud_ipd/services/__init__.py
pyicloud_ipd/services/photos.py
icloudpd-1.32.2.dist-info/METADATA
icloudpd-1.32.2.dist-info/WHEEL
icloudpd-1.32.2.dist-info/entry_points.txt
icloudpd-1.32.2.dist-info/top_level.txt
icloudpd-1.32.2.dist-info/RECORD
