Metadata-Version: 2.4
Name: icloudpd
Version: 1.32.2
Summary: icloudpd is a command-line tool to download photos and videos from iCloud.
Author: The iCloud Photo Downloader Authors
License: The MIT License (MIT)
Project-URL: Homepage, https://github.com/icloud-photos-downloader/icloud_photos_downloader
Keywords: icloud,photo
Classifier: Intended Audience :: End Users/Desktop
Classifier: Operating System :: OS Independent
Classifier: Programming Language :: Python :: 3
Classifier: License :: OSI Approved :: MIT License
Requires-Python: <3.14,>=3.10
License-File: LICENSE.md
Requires-Dist: requests==2.32.3
Requires-Dist: schema==0.7.7
Requires-Dist: tqdm==4.67.1
Requires-Dist: piexif==1.1.3
Requires-Dist: urllib3==1.26.20
Requires-Dist: typing_extensions==4.14.0
Requires-Dist: Flask==3.1.1
Requires-Dist: waitress==3.0.2
Requires-Dist: tzlocal==5.3.1
Requires-Dist: pytz==2025.2
Requires-Dist: certifi==2025.4.26
Requires-Dist: keyring==25.6.0
Requires-Dist: keyrings-alt==5.0.2
Requires-Dist: srp==1.0.22
Dynamic: license-file
